dyn_rl_benchmarks/__init__.py
dyn_rl_benchmarks/envs/__init__.py
dyn_rl_benchmarks/envs/drawbridge.py
dyn_rl_benchmarks/envs/platforms_env.py
dyn_rl_benchmarks/envs/platforms_time_env.py
dyn_rl_benchmarks/envs/tennis_2d.py
dyn_rl_benchmarks/envs/assets/__init__.py
dyn_rl_benchmarks/envs/assets/drawbridge.mtl
dyn_rl_benchmarks/envs/assets/drawbridge.obj
dyn_rl_benchmarks/utils/__init__.py
dyn_rl_benchmarks/utils/graphics_utils.py
dyn_rl_benchmarks/utils/pyglet_utils.py
dyn_rl_benchmarks-1.0.3.dist-info/LICENSE.txt
dyn_rl_benchmarks-1.0.3.dist-info/METADATA
dyn_rl_benchmarks-1.0.3.dist-info/WHEEL
dyn_rl_benchmarks-1.0.3.dist-info/top_level.txt
dyn_rl_benchmarks-1.0.3.dist-info/RECORD
