Metadata-Version: 2.1
Name: dyn-rl-benchmarks
Version: 1.0.3
Summary: Reinforcement learning benchmark problems set in dynamic environments.
Home-page: https://github.com/martius-lab/dynamic-rl-benchmarks
Author: Nico Gürtler
Author-email: nico.guertler@tuebingen.mpg.de
License: MIT
Keywords: reinforcement learning,reinforcement learning environmnts
Platform: UNKNOWN
License-File: LICENSE.txt
Requires-Dist: numpy
Requires-Dist: gym
Requires-Dist: roboball2d
Requires-Dist: wavefront-reader
